pysimplebase/__init__.py
pysimplebase/pysimplebase.py
pysimplebase-0.0.8.dist-info/LICENSE
pysimplebase-0.0.8.dist-info/METADATA
pysimplebase-0.0.8.dist-info/WHEEL
pysimplebase-0.0.8.dist-info/top_level.txt
pysimplebase-0.0.8.dist-info/RECORD
