Metadata-Version: 2.1
Name: pysimplebase
Version: 0.0.8
Summary: High performance JSON-oriented database
Author-email: Dmitry Vorontsov <dv1555@hotmail.com>
Project-URL: Homepage, https://simplebase.readthedocs.io/en/latest/#
Classifier: Programming Language :: Python :: 3
Classifier: License :: OSI Approved :: GNU General Public License v3 or later (GPLv3+)
Classifier: Operating System :: OS Independent
Requires-Python: >=3.7
License-File: LICENSE
Requires-Dist: filelock
Requires-Dist: msgspec
